requests_signer/__init__.py
requests_signer/requests_signer.py
requests_signer-0.1.1.dist-info/METADATA
requests_signer-0.1.1.dist-info/WHEEL
requests_signer-0.1.1.dist-info/top_level.txt
requests_signer-0.1.1.dist-info/RECORD
